{"boards": [{"name": "COMMUNITY RELATIONS BOARD", "location": "Room 11", "members": [{"name": "[vacant]", "location": "", "department": "COMMUNITY RELATIONS BOARD", "position": "Director", "division": ""}, {"name": "Mayor Frank G. Jackson", "location": "", "department": "COMMUNITY RELATIONS BOARD", "position": "Chairman Ex-Officio", "division": ""}, {"name": "Rev. Charles Lucas, Jr", "location": "", "department": "COMMUNITY RELATIONS BOARD", "position": "Vice-Chairman", "division": ""}, {"name": "Kevin Conwell", "location": "", "department": "COMMUNITY RELATIONS BOARD", "position": "Member", "division": ""}, {"name": "Matthew Zone", "location": "", "department": "COMMUNITY RELATIONS BOARD", "position": "Member", "division": ""}, {"name": "City Council Representatives", "location": "", "department": "COMMUNITY RELATIONS BOARD", "position": "Member", "division": ""}, {"name": "Charles L Patton, Jr.", "location": "", "department": "COMMUNITY RELATIONS BOARD", "position": "Member", "division": ""}, {"name": "Paula Castleberry", "location": "", "department": "COMMUNITY RELATIONS BOARD", "position": "Member", "division": ""}, {"name": "Emmett Saunders", "location": "", "department": "COMMUNITY RELATIONS BOARD", "position": "Member", "division": ""}, {"name": "John Banno", "location": "", "department": "COMMUNITY RELATIONS BOARD", "position": "Member", "division": ""}, {"name": "Kathryn M. Hall", "location": "", "department": "COMMUNITY RELATIONS BOARD", "position": "Member", "division": ""}, {"name": "Evangeline Hardaway", "location": "", "department": "COMMUNITY RELATIONS BOARD", "position": "Member", "division": ""}, {"name": "Janet Jankura", "location": "", "department": "COMMUNITY RELATIONS BOARD", "position": "Member", "division": ""}, {"name": "Gia Hoa Ryan", "location": "", "department": "COMMUNITY RELATIONS BOARD", "position": "Member", "division": ""}, {"name": "Rev. Jesse Harris", "location": "", "department": "COMMUNITY RELATIONS BOARD", "position": "Member", "division": ""}, {"name": "Magda Gomez", "location": "", "department": "COMMUNITY RELATIONS BOARD", "position": "Member", "division": ""}, {"name": "Fred J Livingstone", "location": "", "department": "COMMUNITY RELATIONS BOARD", "position": "Member", "division": ""}, {"name": "Margot James Copeland", "location": "", "department": "COMMUNITY RELATIONS BOARD", "position": "Member", "division": ""}]}, {"name": "BOARD OF ZONING APPEALS", "location": "Room 516", "members": [{"name": "Carol A. Johnson", "location": "", "department": "BOARD OF ZONING APPEALS", "position": "Chairman", "division": ""}, {"name": "s", "location": "", "department": "BOARD OF ZONING APPEALS", "position": "Member", "division": ""}, {"name": "Margaret Hopkins", "location": "", "department": "BOARD OF ZONING APPEALS", "position": "Member", "division": ""}, {"name": "Ozell Dobbins", "location": "", "department": "BOARD OF ZONING APPEALS", "position": "Member", "division": ""}, {"name": "Joan Shaver Washington", "location": "", "department": "BOARD OF ZONING APPEALS", "position": "Member", "division": ""}, {"name": "Tim Donovan", "location": "", "department": "BOARD OF ZONING APPEALS", "position": "Member", "division": ""}, {"name": "[vacant]", "location": "", "department": "BOARD OF ZONING APPEALS", "position": "Secretary", "division": ""}]}, {"name": "BOARD OF BUILDING STANDARDS AND BUILDING APPEALS", "location": "Room 516", "members": [{"name": "J. F. Denk", "location": "", "department": "BOARD OF BUILDING STANDARDS AND BUILDING APPEALS", "position": "Chairman", "division": ""}, {"name": "[vacant]", "location": "", "department": "BOARD OF BUILDING STANDARDS AND BUILDING APPEALS", "position": "Arthur Saunders", "division": ""}, {"name": "Alternate Members - D. Cox", "location": "E. P. O'Brien, Richard Pace, J.S. Sullivan", "department": "BOARD OF BUILDING STANDARDS AND BUILDING APPEALS", "position": "P Frank", "division": ""}]}, {"name": "BOARD OF REVISION OF ASSESSMENTS", "location": "", "members": [{"name": "[vacant]", "location": "", "department": "BOARD OF REVISION OF ASSESSMENTS", "position": "President", "division": ""}, {"name": "[vacant]", "location": "", "department": "BOARD OF REVISION OF ASSESSMENTS", "position": "Secretary", "division": ""}, {"name": "Council President Martin J. Sweeney", "location": "", "department": "BOARD OF REVISION OF ASSESSMENTS", "position": "", "division": ""}]}, {"name": "BOARD OF SIDEWALK APPEALS", "location": "", "members": [{"name": "[vacant]", "location": "", "department": "BOARD OF SIDEWALK APPEALS", "position": "", "division": ""}, {"name": "[vacant]", "location": "", "department": "BOARD OF SIDEWALK APPEALS", "position": "Law Director", "division": ""}, {"name": "[vacant]", "location": "", "department": "BOARD OF SIDEWALK APPEALS", "position": "Councilman", "division": ""}]}, {"name": "BOARD OF REVIEW - (Municipal Income Tax)", "location": "", "members": [{"name": "[vacant]", "location": "", "department": "BOARD OF REVIEW - (Municipal Income Tax)", "position": "Law Director", "division": ""}, {"name": "Council President Martin J. Sweeney", "location": "", "department": "BOARD OF REVIEW - (Municipal Income Tax)", "position": "", "division": ""}]}, {"name": "FAIR EMPLOYMENT WAGE BOARD", "location": "Room 210 ", "members": [{"name": "Gerald Meyer", "location": "", "department": "FAIR EMPLOYMENT WAGE BOARD", "position": "Member", "division": ""}, {"name": "Chair", "location": "", "department": "FAIR EMPLOYMENT WAGE BOARD", "position": "Member", "division": ""}, {"name": "Angela Caldwell", "location": "", "department": "FAIR EMPLOYMENT WAGE BOARD", "position": "Member", "division": ""}, {"name": "Vice Chair", "location": "", "department": "FAIR EMPLOYMENT WAGE BOARD", "position": "Member", "division": ""}, {"name": "Patrick Gallagher", "location": "", "department": "FAIR EMPLOYMENT WAGE BOARD", "position": "Kathryn Jackson", "division": ""}, {"name": "Draydean McCaleb", "location": "Ed Romero", "department": "FAIR EMPLOYMENT WAGE BOARD", "position": "Council Member ____________", "division": ""}]}, {"name": "FAIR HOUSING BOARD", "location": "", "members": [{"name": "Charles See", "location": "", "department": "FAIR HOUSING BOARD", "position": "Member", "division": ""}, {"name": "Chair", "location": "", "department": "FAIR HOUSING BOARD", "position": "Member", "division": ""}, {"name": "Cindy Barber", "location": "", "department": "FAIR HOUSING BOARD", "position": "Member", "division": ""}, {"name": "Vice Chair", "location": "", "department": "FAIR HOUSING BOARD", "position": "Member", "division": ""}, {"name": "Michael Doud", "location": "", "department": "FAIR HOUSING BOARD", "position": "Member", "division": ""}, {"name": "Doris Honsa", "location": "", "department": "FAIR HOUSING BOARD", "position": "Member", "division": ""}, {"name": "Richard Lenard", "location": "", "department": "FAIR HOUSING BOARD", "position": "Member", "division": ""}]}, {"name": "HOUSING ADVISORY BOARD", "location": "Room 310 ", "members": [{"name": "Keith Brown", "location": "", "department": "HOUSING ADVISORY BOARD", "position": "Member", "division": ""}, {"name": "Terri Hamilton Brown", "location": "", "department": "HOUSING ADVISORY BOARD", "position": "Member", "division": ""}, {"name": "Vickie Eaton-Johnson", "location": "", "department": "HOUSING ADVISORY BOARD", "position": "Member", "division": ""}, {"name": "Mike Foley", "location": "", "department": "HOUSING ADVISORY BOARD", "position": "Member", "division": ""}, {"name": "Eric Hodderson", "location": "", "department": "HOUSING ADVISORY BOARD", "position": "Member", "division": ""}, {"name": "Janet Loehr", "location": "", "department": "HOUSING ADVISORY BOARD", "position": "Member", "division": ""}, {"name": "Mark McDermott", "location": "", "department": "HOUSING ADVISORY BOARD", "position": "Member", "division": ""}, {"name": "Marcia Nolan", "location": "", "department": "HOUSING ADVISORY BOARD", "position": "Member", "division": ""}, {"name": "David Perkowski", "location": "", "department": "HOUSING ADVISORY BOARD", "position": "Member", "division": ""}, {"name": "Joan Shaver Washington", "location": "", "department": "HOUSING ADVISORY BOARD", "position": "Member", "division": ""}, {"name": "Keith Sutton", "location": "", "department": "HOUSING ADVISORY BOARD", "position": "Member", "division": ""}]}, {"name": "POLICE REVIEW BOARD", "location": "", "members": [{"name": "Thomas Jones", "location": "", "department": "POLICE REVIEW BOARD", "position": "Member", "division": ""}, {"name": "Board Chair Person", "location": "", "department": "POLICE REVIEW BOARD", "position": "Member", "division": ""}, {"name": "Vernon Collier", "location": "", "department": "POLICE REVIEW BOARD", "position": "Member", "division": ""}, {"name": "Vermel Whalen", "location": "", "department": "POLICE REVIEW BOARD", "position": "Member", "division": ""}, {"name": "Nancy Cronin", "location": "", "department": "POLICE REVIEW BOARD", "position": "Member", "division": ""}, {"name": "Elvin Vauss", "location": "", "department": "POLICE REVIEW BOARD", "position": "Member", "division": ""}]}, {"name": "BOARD OF EXAMINERS OF ELECTRICIANS", "location": "", "members": [{"name": "Samuel Montfort", "location": "", "department": "BOARD OF EXAMINERS OF ELECTRICIANS", "position": "Chairman", "division": ""}, {"name": "Donald Baulknilght", "location": "", "department": "BOARD OF EXAMINERS OF ELECTRICIANS", "position": "Member", "division": ""}, {"name": "Anton J. Eichmuller", "location": "", "department": "BOARD OF EXAMINERS OF ELECTRICIANS", "position": "Member", "division": ""}, {"name": "J. Gilbert Steele", "location": "", "department": "BOARD OF EXAMINERS OF ELECTRICIANS", "position": "Member", "division": ""}, {"name": "Raymond Ossovicki", "location": "", "department": "BOARD OF EXAMINERS OF ELECTRICIANS", "position": "Member", "division": ""}, {"name": "Chief Electrical Inspector", "location": "", "department": "BOARD OF EXAMINERS OF ELECTRICIANS", "position": "Member", "division": ""}, {"name": "Laszlo V. Kemes", "location": "", "department": "BOARD OF EXAMINERS OF ELECTRICIANS", "position": "Member", "division": ""}, {"name": "to the Boar", "location": "", "department": "BOARD OF EXAMINERS OF ELECTRICIANS", "position": "Member", "division": ""}, {"name": "to the Board", "location": "", "department": "BOARD OF EXAMINERS OF ELECTRICIANS", "position": "Secretary", "division": ""}]}, {"name": "BOARD OF EXAMINERS OF PLUMBERS", "location": "", "members": [{"name": "Joseph Gyorky", "location": "", "department": "BOARD OF EXAMINERS OF PLUMBERS", "position": "Chairman", "division": ""}, {"name": "Earl S. Bumgarner", "location": "", "department": "BOARD OF EXAMINERS OF PLUMBERS", "position": "Member", "division": ""}, {"name": "Alfred Fowler", "location": "", "department": "BOARD OF EXAMINERS OF PLUMBERS", "position": "Member", "division": ""}, {"name": "Jozef Valencik", "location": "", "department": "BOARD OF EXAMINERS OF PLUMBERS", "position": "Member", "division": ""}, {"name": "Lawrence Skule", "location": "", "department": "BOARD OF EXAMINERS OF PLUMBERS", "position": "Member", "division": ""}, {"name": "Chief Plumbing Inspector", "location": "", "department": "BOARD OF EXAMINERS OF PLUMBERS", "position": "Member", "division": ""}, {"name": "Laszlo V Kemes", "location": "", "department": "BOARD OF EXAMINERS OF PLUMBERS", "position": "Member", "division": ""}, {"name": "to the Boar", "location": "", "department": "BOARD OF EXAMINERS OF PLUMBERS", "position": "Member", "division": ""}, {"name": "to the Board", "location": "", "department": "BOARD OF EXAMINERS OF PLUMBERS", "position": "Secretary", "division": ""}]}], "departments": [{"name": "DEPT. OF LAW", "location": "", "divisions": {}, "members": [{"name": "[vacant]", "location": "Richard F. Horvath, Chief Counsel, Room 106", "department": "DEPT. OF LAW", "position": "Director", "division": ""}, {"name": "Karen E. Martines", "location": "Room 100", "department": "DEPT. OF LAW", "position": "Law Librarian", "division": ""}]}, {"name": "DEPT. OF FINANCE", "location": "", "divisions": ["Assessments and Licenses", "City Treasury", "Financial Reporting and Control", "Information Technology and Services", "Purchases and Supplies", "Printing and Reproduction", "Taxation"], "members": [{"name": "Dedrick Stephens", "location": "Room 122", "department": "DEPT. OF FINANCE", "position": "Commissioner", "division": "Assessments and Licenses"}, {"name": "Algeron Walker", "location": "Room 115", "department": "DEPT. OF FINANCE", "position": "Treasurer", "division": "City Treasury"}, {"name": "James Gentile", "location": "Room 18", "department": "DEPT. OF FINANCE", "position": "Controller", "division": "Financial Reporting and Control"}, {"name": "Douglas Divish", "location": "1404 East 9th Street", "department": "DEPT. OF FINANCE", "position": "Commissioner", "division": "Information Technology and Services"}, {"name": "James E. Hardy", "location": "Room 128", "department": "DEPT. OF FINANCE", "position": "Commissioner", "division": "Purchases and Supplies"}, {"name": "Michael Hewitt", "location": "1735 Lakeside Avenue", "department": "DEPT. OF FINANCE", "position": "Commissioner", "division": "Printing and Reproduction"}, {"name": "Nassim Lynch", "location": "1701 Lakeside Avenue", "department": "DEPT. OF FINANCE", "position": "Tax Administrator", "division": "Taxation"}]}, {"name": "DEPT. OF PUBLIC UTILITIES", "location": "", "divisions": ["Cleveland Public Power", "Street Lighting Bureau", "Utilities Fiscal Control", "Water", "Water Pollution Control"], "members": [{"name": "James F. Majer", "location": "", "department": "DEPT. OF PUBLIC UTILITIES", "position": "Commissioner", "division": "Cleveland Public Power"}, {"name": "[vacant]", "location": "", "department": "DEPT. OF PUBLIC UTILITIES", "position": "Acting Chief", "division": "Street Lighting Bureau"}, {"name": "Dennis Nichols", "location": "", "department": "DEPT. OF PUBLIC UTILITIES", "position": "Commissioner", "division": "Utilities Fiscal Control"}, {"name": "John Christopher Nielson", "location": "", "department": "DEPT. OF PUBLIC UTILITIES", "position": "Commissioner", "division": "Water"}, {"name": "Ollie Shaw", "location": "", "department": "DEPT. OF PUBLIC UTILITIES", "position": "Commissioner", "division": "Water Pollution Control"}]}, {"name": "DEPT. OF PORT CONTROL", "location": "", "divisions": {}, "members": [{"name": "John Mok", "location": "", "department": "DEPT. OF PORT CONTROL", "position": "Interim Director", "division": ""}, {"name": "Cleveland Hopkins International Airport", "location": "", "department": "DEPT. OF PORT CONTROL", "position": "5300 Riverside Drive", "division": ""}, {"name": "Burke Lakefront Airport - Khalid Bahhur", "location": "", "department": "DEPT. OF PORT CONTROL", "position": "Commissioner", "division": ""}, {"name": "Cleveland Hopkins International Airport - Fred Szabo", "location": "", "department": "DEPT. OF PORT CONTROL", "position": "Commissioner", "division": ""}]}, {"name": "DEPT. OF PUBLIC SERVICE", "location": "", "divisions": ["Engineering and Construction", "Motor Vehicle Maintenance", "Streets", "Traffic Engineering", "Waste Collection and Disposal"], "members": [{"name": "Randall E. DeVaul", "location": "Room 518", "department": "DEPT. OF PUBLIC SERVICE", "position": "Commissioner", "division": "Engineering and Construction"}, {"name": "Daniel A. Novak", "location": "Harvard Yards", "department": "DEPT. OF PUBLIC SERVICE", "position": "Commissioner", "division": "Motor Vehicle Maintenance"}, {"name": "Randell T. Scott", "location": "Room 25", "department": "DEPT. OF PUBLIC SERVICE", "position": "Commissioner", "division": "Streets"}, {"name": "Robert Mavec", "location": "4150 East 49th Street, Building #1", "department": "DEPT. OF PUBLIC SERVICE", "position": "Commissioner", "division": "Traffic Engineering"}, {"name": "Ron Owens", "location": "5600 Carnegie Avenue", "department": "DEPT. OF PUBLIC SERVICE", "position": "Commissioner", "division": "Waste Collection and Disposal"}]}, {"name": "DEPT. OF PUBLIC HEALTH", "location": "", "divisions": ["Correction", "Environment", "Health"], "members": [{"name": "Robert Taskey", "location": "Cleveland House of Corrections, 4041 Northfield Rd", "department": "DEPT. OF PUBLIC HEALTH", "position": "Commissioner", "division": "Correction"}, {"name": "Willie Bess", "location": "Mural Building, 1925 St. Clair Ave", "department": "DEPT. OF PUBLIC HEALTH", "position": "Commissioner", "division": "Environment"}, {"name": "Anjou Parekh", "location": "Mural Building, 1925 St. Clair Ave", "department": "DEPT. OF PUBLIC HEALTH", "position": "Commissioner", "division": "Health"}]}, {"name": "DEPT. OF PUBLIC SAFETY", "location": "", "divisions": ["Emergency Medical Service", "Fire", "Police"], "members": [{"name": "Edward Eckart", "location": "1708 South Pointe Drive", "department": "DEPT. OF PUBLIC SAFETY", "position": "Commissioner", "division": "Emergency Medical Service"}, {"name": "Paul A. Stubbs", "location": "1645 Superior Avenue", "department": "DEPT. OF PUBLIC SAFETY", "position": "Chief", "division": "Fire"}, {"name": "Michael C. McGrath", "location": "Police Hdqtrs. Bldg., 1300 Ontario Street", "department": "DEPT. OF PUBLIC SAFETY", "position": "Chief", "division": "Police"}]}, {"name": "DEPT. OF PARKS, RECREATION & PROPERTIES", "location": "", "divisions": ["Public Auditorium", "Parking Facilities", "Public Auditorium", "Park Maintenance and Properties", "Public Auditorium", "Property Management", "Recreation"], "members": [{"name": "East 6th Street and Lakeside Avenue", "location": "", "department": "DEPT. OF PARKS, RECREATION & PROPERTIES", "position": "", "division": "Public Auditorium"}, {"name": "[vacant]", "location": "", "department": "DEPT. OF PARKS, RECREATION & PROPERTIES", "position": "Commissioner", "division": "Parking Facilities"}, {"name": "East 6th Street and Lakeside Avenue", "location": "", "department": "DEPT. OF PARKS, RECREATION & PROPERTIES", "position": "", "division": "Public Auditorium"}, {"name": "Richard L. Silva", "location": "", "department": "DEPT. OF PARKS, RECREATION & PROPERTIES", "position": "Commissioner", "division": "Park Maintenance and Properties"}, {"name": "East 6th Street and Lakeside Avenue", "location": "", "department": "DEPT. OF PARKS, RECREATION & PROPERTIES", "position": "", "division": "Public Auditorium"}, {"name": "Tom Nagle", "location": "East 49th Street & Harvard", "department": "DEPT. OF PARKS, RECREATION & PROPERTIES", "position": "Commissioner", "division": "Property Management"}, {"name": "Michael Cox", "location": "Room 8 Research, Planning & Development", "department": "DEPT. OF PARKS, RECREATION & PROPERTIES", "position": "Commissioner", "division": "Recreation"}]}, {"name": "DEPT. OF BUILDING AND HOUSING", "location": "", "divisions": ["Construction Permitting"], "members": [{"name": "Timothy R. Wolosz", "location": "", "department": "DEPT. OF BUILDING AND HOUSING", "position": "Commissioner", "division": "Construction Permitting"}]}, {"name": "DEPT. OF PERSONNELAND HUMAN RESOURCES", "location": "", "divisions": {}, "members": [{"name": "Sue Rudman", "location": "Room 121", "department": "DEPT. OF PERSONNELAND HUMAN RESOURCES", "position": "Interim Director", "division": ""}]}, {"name": "DEPT. OF ECONOMIC DEVELOPMENT", "location": "", "divisions": {}, "members": [{"name": "[vacant]", "location": "Room 210", "department": "DEPT. OF ECONOMIC DEVELOPMENT", "position": "Director", "division": ""}]}, {"name": "DEPT. OF AGING", "location": "", "divisions": {}, "members": [{"name": "[vacant]", "location": "Room 122", "department": "DEPT. OF AGING", "position": "Director", "division": ""}]}, {"name": "DEPT. OF CONSUMER AFFAIRS", "location": "", "divisions": {}, "members": [{"name": "Kenya Taylor", "location": "", "department": "DEPT. OF CONSUMER AFFAIRS", "position": "Interim Director", "division": ""}]}], "commissions": [{"name": "CIVIL SERVICE COMMISSION", "location": "Room 119", "members": [{"name": "Reynaldo Galindo", "location": "", "department": "CIVIL SERVICE COMMISSION", "position": "President", "division": ""}, {"name": "Rev. Earl Preston", "location": "", "department": "CIVIL SERVICE COMMISSION", "position": "Vice President", "division": ""}, {"name": "Jonalyn M. Krupka", "location": "", "department": "CIVIL SERVICE COMMISSION", "position": "Secretary", "division": ""}, {"name": "s: Diane M. Downing", "location": "", "department": "CIVIL SERVICE COMMISSION", "position": "William Morrison", "division": ""}]}, {"name": "SINKING FUND COMMISSION", "location": "", "members": [{"name": "Frank G. Jackson", "location": "", "department": "SINKING FUND COMMISSION", "position": "President", "division": ""}, {"name": "Council President Martin J. Sweeney", "location": "", "department": "SINKING FUND COMMISSION", "position": "", "division": ""}, {"name": "Betsy Hruby", "location": "", "department": "SINKING FUND COMMISSION", "position": "Assistant Secretary", "division": ""}, {"name": "[vacant]", "location": "", "department": "SINKING FUND COMMISSION", "position": "Director", "division": ""}]}, {"name": "CITY PLANNING COMMISSION", "location": "Room 501 ", "members": [{"name": "[vacant]", "location": "", "department": "CITY PLANNING COMMISSION", "position": "Director", "division": ""}, {"name": "Anthony J. Coyne", "location": "", "department": "CITY PLANNING COMMISSION", "position": "Chairman", "division": ""}, {"name": "David Bowen", "location": "", "department": "CITY PLANNING COMMISSION", "position": "Member", "division": ""}, {"name": "Lillian Kuri", "location": "", "department": "CITY PLANNING COMMISSION", "position": "Member", "division": ""}, {"name": "Lawrence A. Lumpkin", "location": "", "department": "CITY PLANNING COMMISSION", "position": "Member", "division": ""}, {"name": "Gloria Jean Pinkney", "location": "", "department": "CITY PLANNING COMMISSION", "position": "Member", "division": ""}, {"name": "Rev. Sam Edward Small", "location": "", "department": "CITY PLANNING COMMISSION", "position": "Member", "division": ""}]}, {"name": "FAIR CAMPAIGN FINANCE COMMISSION", "location": "", "members": [{"name": "Chris Warren", "location": "", "department": "FAIR CAMPAIGN FINANCE COMMISSION", "position": "Member", "division": ""}, {"name": "C. Ellen Connally", "location": "", "department": "FAIR CAMPAIGN FINANCE COMMISSION", "position": "Member", "division": ""}, {"name": "Hillary S. Taylor", "location": "", "department": "FAIR CAMPAIGN FINANCE COMMISSION", "position": "Member", "division": ""}]}, {"name": "CLEVELAND BOXING AND WRESTLING COMMISSION", "location": "", "members": [{"name": "Robert Jones", "location": "", "department": "CLEVELAND BOXING AND WRESTLING COMMISSION", "position": "Chairman", "division": ""}, {"name": "Clint Martin", "location": "", "department": "CLEVELAND BOXING AND WRESTLING COMMISSION", "position": "Member", "division": ""}, {"name": "Mark Rivera", "location": "", "department": "CLEVELAND BOXING AND WRESTLING COMMISSION", "position": "Member", "division": ""}]}, {"name": "MORAL CLAIMS COMMISSION", "location": "", "members": [{"name": "[vacant]", "location": "", "department": "MORAL CLAIMS COMMISSION", "position": "Law Director", "division": ""}, {"name": "", "location": "", "department": "MORAL CLAIMS COMMISSION", "position": "Chairman", "division": ""}, {"name": "[vacant]", "location": "", "department": "MORAL CLAIMS COMMISSION", "position": "", "division": ""}, {"name": "Council President Martin J. Sweeney", "location": "", "department": "MORAL CLAIMS COMMISSION", "position": "", "division": ""}, {"name": "Dona Brady", "location": "", "department": "MORAL CLAIMS COMMISSION", "position": "Councilman", "division": ""}, {"name": "[vacant]", "location": "", "department": "MORAL CLAIMS COMMISSION", "position": "Councilman", "division": ""}]}, {"name": "CLEVELAND LANDMARKS COMMISSION", "location": "Room 519 ", "members": [{"name": "James D. Gibans", "location": "", "department": "CLEVELAND LANDMARKS COMMISSION", "position": "Member", "division": ""}, {"name": "Chair", "location": "", "department": "CLEVELAND LANDMARKS COMMISSION", "position": "Member", "division": ""}, {"name": "Randall B. Shorr", "location": "", "department": "CLEVELAND LANDMARKS COMMISSION", "position": "Member", "division": ""}, {"name": "Vice Chair", "location": "", "department": "CLEVELAND LANDMARKS COMMISSION", "position": "Member", "division": ""}, {"name": "Kevin Dreyfuss-Wells", "location": "", "department": "CLEVELAND LANDMARKS COMMISSION", "position": "India Pierce Lee", "division": ""}, {"name": "Laura M. Noble", "location": "N. Kurt Wiebusch, Council Member ____________, Robert Jackimowicz", "department": "CLEVELAND LANDMARKS COMMISSION", "position": "____________", "division": ""}, {"name": "Robert Keiser", "location": "", "department": "CLEVELAND LANDMARKS COMMISSION", "position": "Secretary", "division": ""}]}]}